affo_event_service/__init__.py
affo_event_service/application.py
affo_event_service/celery.py
affo_event_service/cli.py
affo_event_service/settings.py
affo_event_service/wsgi.py
affo_event_service/api/__init__.py
affo_event_service/api/event.py
affo_event_service/api/postback.py
affo_event_service/extensions/__init__.py
affo_event_service/extensions/clickhouse.py
affo_event_service/migrations/0001_initial.py
affo_event_service/migrations/0002_add_summary.py
affo_event_service/migrations/__init__.py
affo_event_service/models/__init__.py
affo_event_service/models/event.py
affo_event_service/models/postback.py
affo_event_service/spec/openapi.yaml
affo_event_service/tasks/__init__.py
affo_event_service/tasks/postback.py
affo_event_service-1.0.1.dist-info/LICENSE
affo_event_service-1.0.1.dist-info/METADATA
affo_event_service-1.0.1.dist-info/WHEEL
affo_event_service-1.0.1.dist-info/entry_points.txt
affo_event_service-1.0.1.dist-info/top_level.txt
affo_event_service-1.0.1.dist-info/RECORD
