Metadata-Version: 2.1
Name: affo-event-service
Version: 1.0.1
Summary: UNKNOWN
Home-page: https://github.com/affoio/affo-event-service
Author: Aleksey Dalekin
Author-email: ald@affo.io
License: BSD
Keywords: email service
Platform: any
Classifier: Development Status :: 3 - Alpha
Classifier: License :: OSI Approved :: BSD License
Classifier: Topic :: System :: Distributed Computing
Classifier: Intended Audience :: Developers
Classifier: Programming Language :: Python
Classifier: Programming Language :: Python :: 3.5
Classifier: Programming Language :: Python :: 3.6
Classifier: Programming Language :: Python :: 3.7
Classifier: Programming Language :: Python :: Implementation :: CPython
Classifier: Operating System :: OS Independent
Requires-Dist: Flask-Script (>=2.0.6)
Requires-Dist: celery (>=4.2.1)
Requires-Dist: connexion (>=2.2.0)
Requires-Dist: connexion-buzz (>=0.2.1)
Requires-Dist: dynaconf (>=2.0.3)
Requires-Dist: flask-marshmallow (==0.10.1)
Requires-Dist: infi.clickhouse-orm (==1.2.0)
Requires-Dist: marshmallow (==3.3.0)
Requires-Dist: redis (>=3.2.0)
Requires-Dist: requests (>=2.21.0)
Requires-Dist: sentry-sdk[flask] (>=0.7.10)
Requires-Dist: uWSGI (>=2.0.18)
